LICENSE
MANIFEST.in
README.md
setup.py
django_userplus.egg-info/PKG-INFO
django_userplus.egg-info/SOURCES.txt
django_userplus.egg-info/dependency_links.txt
django_userplus.egg-info/not-zip-safe
django_userplus.egg-info/requires.txt
django_userplus.egg-info/top_level.txt
userplus/__init__.py
userplus/admin.py
userplus/apps.py
userplus/backends.py
userplus/forms.py
userplus/models.py
userplus/tests.py
userplus/urls.py
userplus/validators.py
userplus/views.py
userplus/lib/__init__.py
userplus/lib/utils.py
userplus/static/userplus/js/fb-auth.js