Metadata-Version: 1.1
Name: django-userplus
Version: 0.3.3
Summary: Extended Auth User module for Django
Home-page: https://github.com/ifedapoolarewaju/django-userplus.git
Author: Ifedapo Olarewaju
Author-email: ifedapoolarewaju@gmail.com
License: MIT
Platform: UNKNOWN
Classifier: Environment :: Web Environment
Classifier: Intended Audience :: Developers
Classifier: License :: OSI Approved :: MIT License
Classifier: Operating System :: OS Independent
Classifier: Programming Language :: Python
Classifier: Framework :: Django
